{
    "code": "OK",
    "data": [
        {
            "_id": "65b4faef1cb9c378e8f16904",
            "title": "Data Science",
            "isRoot": true,
            "type": "folder",
            "children": [
                {
                    "_id": "65b4fba89d3797e52ed95703",
                    "title": "iphone10",
                    "isRoot": false,
                    "type": "file",
                    "parentId": "65b4faef1cb9c378e8f16904",
                    "children": [],
                    "userId": "65b4faed1cb9c378e8f16902",
                    "createdBy": {
                        "email": "pvnk17@gmail.com",
                        "username": "pvnk17",
                        "userId": "65b4faed1cb9c378e8f16902",
                        "iat": 1706359535
                    },
                    "data": {
                        "text": "{\"root\":{\"children\":[{\"children\":[{\"detail\":0,\"format\":0,\"mode\":\"normal\",\"style\":\"\",\"text\":\"iphone1675\",\"type\":\"text\",\"version\":1}],\"direction\":\"ltr\",\"format\":\"\",\"indent\":0,\"type\":\"heading\",\"version\":1,\"tag\":\"h1\"},{\"children\":[],\"direction\":null,\"format\":\"\",\"indent\":0,\"type\":\"paragraph\",\"version\":1},{\"children\":[{\"detail\":0,\"format\":0,\"mode\":\"normal\",\"style\":\"\",\"text\":\"text4\",\"type\":\"text\",\"version\":1}],\"direction\":\"ltr\",\"format\":\"\",\"indent\":0,\"type\":\"paragraph\",\"version\":1}],\"direction\":\"ltr\",\"format\":\"\",\"indent\":0,\"type\":\"root\",\"version\":1}}"
                    },
                    "createdAt": "2024-01-27T12:48:40.094Z",
                    "updatedAt": "2024-02-10T07:43:52.285Z",
                    "__v": 0
                },
                {
                    "_id": "65b4fbe59d3797e52ed95709",
                    "title": "Iphone",
                    "isRoot": false,
                    "type": "folder",
                    "parentId": "65b4faef1cb9c378e8f16904",
                    "children": [
                        {
                            "_id": "65c7201e6abef320365e7c17",
                            "title": "iphone11",
                            "isRoot": false,
                            "type": "file",
                            "parentId": "65b4fbe59d3797e52ed95709",
                            "children": [],
                            "userId": "65b4faed1cb9c378e8f16902",
                            "createdBy": {
                                "email": "pvnk17@gmail.com",
                                "username": "pvnk17",
                                "userId": "65b4faed1cb9c378e8f16902",
                                "iat": 1707487163
                            },
                            "data": {
                                "text": "{\"root\":{\"children\":[{\"children\":[{\"detail\":0,\"format\":0,\"mode\":\"normal\",\"style\":\"\",\"text\":\"iphone1675\",\"type\":\"text\",\"version\":1}],\"direction\":\"ltr\",\"format\":\"\",\"indent\":0,\"type\":\"heading\",\"version\":1,\"tag\":\"h1\"},{\"children\":[],\"direction\":null,\"format\":\"\",\"indent\":0,\"type\":\"paragraph\",\"version\":1},{\"children\":[{\"detail\":0,\"format\":0,\"mode\":\"normal\",\"style\":\"\",\"text\":\"text4\",\"type\":\"text\",\"version\":1}],\"direction\":\"ltr\",\"format\":\"\",\"indent\":0,\"type\":\"paragraph\",\"version\":1}],\"direction\":\"ltr\",\"format\":\"\",\"indent\":0,\"type\":\"root\",\"version\":1}}"
                            },
                            "createdAt": "2024-02-10T07:05:02.183Z",
                            "updatedAt": "2024-02-10T07:42:34.255Z",
                            "__v": 0
                        }
                    ],
                    "userId": "65b4faed1cb9c378e8f16902",
                    "createdBy": {
                        "email": "pvnk17@gmail.com",
                        "username": "pvnk17",
                        "userId": "65b4faed1cb9c378e8f16902",
                        "iat": 1706359535
                    },
                    "data": {
                        "text": ""
                    },
                    "createdAt": "2024-01-27T12:49:41.563Z",
                    "updatedAt": "2024-02-10T07:05:02.282Z",
                    "__v": 0
                },
                {
                    "_id": "65c726fd6abef320365e7c2b",
                    "title": "title 5",
                    "isRoot": false,
                    "type": "folder",
                    "parentId": "65b4faef1cb9c378e8f16904",
                    "children": [
                        {
                            "_id": "65c730c16abef320365e7c4f",
                            "title": "title 1",
                            "isRoot": false,
                            "type": "file",
                            "parentId": "65c726fd6abef320365e7c2b",
                            "children": [],
                            "userId": "65b4faed1cb9c378e8f16902",
                            "createdBy": {
                                "email": "pvnk17@gmail.com",
                                "username": "pvnk17",
                                "userId": "65b4faed1cb9c378e8f16902",
                                "iat": 1707545084
                            },
                            "data": {
                                "text": ""
                            },
                            "createdAt": "2024-02-10T08:16:01.919Z",
                            "updatedAt": "2024-02-10T08:16:01.919Z",
                            "__v": 0
                        },
                        {
                            "_id": "65c730d76abef320365e7c55",
                            "title": "title 5",
                            "isRoot": false,
                            "type": "file",
                            "parentId": "65c726fd6abef320365e7c2b",
                            "children": [],
                            "userId": "65b4faed1cb9c378e8f16902",
                            "createdBy": {
                                "email": "pvnk17@gmail.com",
                                "username": "pvnk17",
                                "userId": "65b4faed1cb9c378e8f16902",
                                "iat": 1707545084
                            },
                            "data": {
                                "text": ""
                            },
                            "createdAt": "2024-02-10T08:16:23.135Z",
                            "updatedAt": "2024-02-10T08:16:23.135Z",
                            "__v": 0
                        }
                    ],
                    "userId": "65b4faed1cb9c378e8f16902",
                    "createdBy": {
                        "email": "pvnk17@gmail.com",
                        "username": "pvnk17",
                        "userId": "65b4faed1cb9c378e8f16902",
                        "iat": 1707545084
                    },
                    "data": {
                        "text": ""
                    },
                    "createdAt": "2024-02-10T07:34:21.934Z",
                    "updatedAt": "2024-02-10T08:16:23.223Z",
                    "__v": 0
                },
                {
                    "_id": "65c72c466abef320365e7c41",
                    "title": "title 3",
                    "isRoot": false,
                    "type": "file",
                    "parentId": "65b4faef1cb9c378e8f16904",
                    "children": [],
                    "userId": "65b4faed1cb9c378e8f16902",
                    "createdBy": {
                        "email": "pvnk17@gmail.com",
                        "username": "pvnk17",
                        "userId": "65b4faed1cb9c378e8f16902",
                        "iat": 1707545084
                    },
                    "data": {
                        "text": ""
                    },
                    "createdAt": "2024-02-10T07:56:54.774Z",
                    "updatedAt": "2024-02-10T07:56:54.774Z",
                    "__v": 0
                },
                {
                    "_id": "65c72fb06abef320365e7c47",
                    "title": "title 1",
                    "isRoot": false,
                    "type": "file",
                    "parentId": "65b4faef1cb9c378e8f16904",
                    "children": [],
                    "userId": "65b4faed1cb9c378e8f16902",
                    "createdBy": {
                        "email": "pvnk17@gmail.com",
                        "username": "pvnk17",
                        "userId": "65b4faed1cb9c378e8f16902",
                        "iat": 1707545084
                    },
                    "data": {
                        "text": ""
                    },
                    "createdAt": "2024-02-10T08:11:28.669Z",
                    "updatedAt": "2024-02-10T08:11:28.669Z",
                    "__v": 0
                }
            ],
            "userId": "65b4faed1cb9c378e8f16902",
            "createdBy": {
                "username": "pvnk17",
                "email": "pvnk17@gmail.com",
                "password": "123456780",
                "_id": "65b4faed1cb9c378e8f16902",
                "__v": 0
            },
            "data": {
                "text": ""
            },
            "createdAt": "2024-01-27T12:45:35.040Z",
            "updatedAt": "2024-02-10T08:11:28.761Z",
            "__v": 0
        }
    ],
    "message": "Success"
}